oneNeuron/__init__.py
oneNeuron/perceptron.py
oneNeuronDemo_pypi_surajk02-0.0.1.dist-info/LICENSE
oneNeuronDemo_pypi_surajk02-0.0.1.dist-info/METADATA
oneNeuronDemo_pypi_surajk02-0.0.1.dist-info/WHEEL
oneNeuronDemo_pypi_surajk02-0.0.1.dist-info/top_level.txt
oneNeuronDemo_pypi_surajk02-0.0.1.dist-info/RECORD
