Metadata-Version: 2.1
Name: oneNeuronDemo-pypi-surajk02
Version: 0.0.1
Summary: A small example package
Home-page: https://github.com/surajk02/oneNeuronDemo_pypi
Author: surajk02
Author-email: sk02@gmail.com
License: UNKNOWN
Project-URL: Bug Tracker, https://github.com/surajk02/oneNeuronDemo_pypi/issues
Platform: UNKNOWN
Classifier: Programming Language :: Python :: 3
Classifier: License :: OSI Approved :: MIT License
Classifier: Operating System :: OS Independent
Requires-Python: >=3.7
License-File: LICENSE
Requires-Dist: numpy
Requires-Dist: tqdm
